directory_visualizer/__init__.py
directory_visualizer/visualizer.py
tests/__init__.py
tests/test_visualizer.py
directory_visualizer-0.1.0.dist-info/LICENSE
directory_visualizer-0.1.0.dist-info/METADATA
directory_visualizer-0.1.0.dist-info/WHEEL
directory_visualizer-0.1.0.dist-info/entry_points.txt
directory_visualizer-0.1.0.dist-info/top_level.txt
directory_visualizer-0.1.0.dist-info/RECORD
