Metadata-Version: 2.1
Name: directory-visualizer
Version: 0.1.0
Summary: A CLI tool to visualize directory structures as Markdown or Mermaid diagrams
Home-page: https://github.com/raselmeya94/directory-visualizer
Author: Md. Rasel Meya
Author-email: raselmeya2194@gmail.com
Classifier: Programming Language :: Python :: 3
Classifier: License :: OSI Approved :: MIT License
Classifier: Operating System :: OS Independent
Requires-Python: >=3.6
License-File: LICENSE
